pycebes/__init__.py
pycebes/config.py
pycebes/core/__init__.py
pycebes/core/client.py
pycebes/core/column.py
pycebes/core/dataframe.py
pycebes/core/exceptions.py
pycebes/core/expressions.py
pycebes/core/functions.py
pycebes/core/pipeline.py
pycebes/core/pipeline_api.py
pycebes/core/sample.py
pycebes/core/schema.py
pycebes/core/session.py
pycebes/core/stages.py
pycebes/internal/__init__.py
pycebes/internal/default_stack.py
pycebes/internal/docker_helpers.py
pycebes/internal/helpers.py
pycebes/internal/implicits.py
pycebes/internal/responses.py
pycebes/internal/serializer.py
pycebes-0.10.2.dist-info/DESCRIPTION.rst
pycebes-0.10.2.dist-info/METADATA
pycebes-0.10.2.dist-info/RECORD
pycebes-0.10.2.dist-info/WHEEL
pycebes-0.10.2.dist-info/metadata.json
pycebes-0.10.2.dist-info/top_level.txt
