Metadata-Version: 2.0
Name: pycebes
Version: 0.10.2
Summary: Python client for Cebes HTTP server.
Home-page: UNKNOWN
Author: Vu Pham
Author-email: vuph@cebes.io
License: Apache 2.0
Platform: UNKNOWN
Requires-Dist: requests
Requires-Dist: requests-toolbelt
Requires-Dist: six
Requires-Dist: pandas (>=0.20.0)
Requires-Dist: tabulate
Requires-Dist: docker
Requires-Dist: docker-pycreds
Requires-Dist: future
